{
  "version": "7",
  "dialect": "sqlite",
  "entries": [
    {
      "idx": 0,
      "version": "6",
      "when": 1772104351566,
      "tag": "0000_spooky_tyger_tiger",
      "breakpoints": true
    },
    {
      "idx": 1,
      "version": "6",
      "when": 1772217093953,
      "tag": "0001_lively_scarecrow",
      "breakpoints": true
    },
    {
      "idx": 2,
      "version": "6",
      "when": 1778543096066,
      "tag": "0002_chunky_lorna_dane",
      "breakpoints": true
    },
    {
      "idx": 3,
      "version": "6",
      "when": 1778543582901,
      "tag": "0003_brief_justice",
      "breakpoints": true
    },
    {
      "idx": 4,
      "version": "6",
      "when": 1778602973317,
      "tag": "0004_gigantic_hammerhead",
      "breakpoints": true
    },
    {
      "idx": 5,
      "version": "6",
      "when": 1778876661094,
      "tag": "0005_wet_zeigeist",
      "breakpoints": true
    },
    {
      "idx": 6,
      "version": "6",
      "when": 1778877700433,
      "tag": "0006_futuristic_peter_quill",
      "breakpoints": true
    },
    {
      "idx": 7,
      "version": "6",
      "when": 1778878067223,
      "tag": "0007_naive_masque",
      "breakpoints": true
    },
    {
      "idx": 8,
      "version": "6",
      "when": 1778888463251,
      "tag": "0008_superb_carnage",
      "breakpoints": true
    }
  ]
}
